{
  "version": "6.0",
  "nxVersion": "18.1.3",
  "deps": {
    "@nestjs/common": "^10.0.2",
    "@nestjs/core": "^10.0.2",
    "@nestjs/platform-express": "^10.0.2",
    "axios": "^1.6.0",
    "next": "14.0.4",
    "react": "18.2.0",
    "react-dom": "18.2.0",
    "reflect-metadata": "^0.1.13",
    "rxjs": "^7.8.0",
    "tslib": "^2.3.0",
    "@nestjs/schematics": "^10.0.1",
    "@nestjs/testing": "^10.0.2",
    "@nx/cypress": "18.1.3",
    "@nx/eslint": "18.1.3",
    "@nx/eslint-plugin": "18.1.3",
    "@nx/jest": "18.1.3",
    "@nx/js": "18.1.3",
    "@nx/nest": "^18.1.3",
    "@nx/next": "^18.1.3",
    "@nx/node": "18.1.3",
    "@nx/react": "18.1.3",
    "@nx/storybook": "^18.1.3",
    "@nx/vite": "18.1.3",
    "@nx/web": "18.1.3",
    "@nx/webpack": "18.1.3",
    "@nx/workspace": "18.1.3",
    "@swc-node/register": "~1.8.0",
    "@swc/cli": "~0.1.62",
    "@swc/core": "~1.3.85",
    "@swc/helpers": "~0.5.2",
    "@testing-library/react": "14.0.0",
    "@types/jest": "^29.4.0",
    "@types/node": "18.16.9",
    "@types/react": "18.2.33",
    "@types/react-dom": "18.2.14",
    "@typescript-eslint/eslint-plugin": "^6.13.2",
    "@typescript-eslint/parser": "^6.13.2",
    "@vitejs/plugin-react": "^4.2.0",
    "@vitest/coverage-v8": "^1.0.4",
    "@vitest/ui": "^1.3.1",
    "autoprefixer": "10.4.13",
    "babel-jest": "^29.4.1",
    "cypress": "^13.6.6",
    "eslint": "~8.48.0",
    "eslint-config-next": "14.0.4",
    "eslint-config-prettier": "^9.0.0",
    "eslint-plugin-cypress": "^2.13.4",
    "eslint-plugin-import": "2.27.5",
    "eslint-plugin-jsx-a11y": "6.7.1",
    "eslint-plugin-react": "7.32.2",
    "eslint-plugin-react-hooks": "4.6.0",
    "jest": "^29.4.1",
    "jest-environment-jsdom": "^29.4.1",
    "jest-environment-node": "^29.4.1",
    "jsdom": "~22.1.0",
    "nx": "18.1.3",
    "postcss": "8.4.21",
    "prettier": "^2.6.2",
    "sass": "1.62.1",
    "storybook": "^7.5.3",
    "tailwindcss": "3.2.7",
    "ts-jest": "^29.1.0",
    "ts-node": "10.9.1",
    "typescript": "~5.3.2",
    "vite": "~5.0.0",
    "vitest": "^1.3.1",
    "webpack-cli": "^5.1.4"
  },
  "pathMappings": {},
  "nxJsonPlugins": [
    {
      "name": "@nx/vite/plugin",
      "options": {
        "buildTargetName": "build",
        "previewTargetName": "preview",
        "testTargetName": "test",
        "serveTargetName": "serve",
        "serveStaticTargetName": "serve-static"
      }
    },
    {
      "name": "@nx/eslint/plugin",
      "options": {
        "targetName": "lint"
      }
    },
    {
      "name": "@nx/webpack/plugin",
      "options": {
        "buildTargetName": "build",
        "serveTargetName": "serve",
        "previewTargetName": "preview"
      }
    },
    {
      "name": "@nx/jest/plugin",
      "options": {
        "targetName": "test"
      }
    },
    {
      "name": "@nx/next/plugin",
      "options": {
        "buildTargetName": "build",
        "devTargetName": "dev",
        "startTargetName": "start",
        "serveStaticTargetName": "serve-static"
      }
    },
    {
      "name": "@nx/cypress/plugin",
      "options": {
        "targetName": "e2e",
        "componentTestingTargetName": "component-test"
      }
    },
    {
      "name": "@nx/storybook/plugin",
      "options": {
        "buildStorybookTargetName": "build-storybook",
        "serveStorybookTargetName": "storybook",
        "testStorybookTargetName": "test-storybook",
        "staticStorybookTargetName": "static-storybook"
      }
    }
  ],
  "fileMap": {
    "projectFileMap": {
      "backend": [
        {
          "file": "apps/backend/.eslintrc.json",
          "hash": "13800677001662881425"
        },
        {
          "file": "apps/backend/jest.config.ts",
          "hash": "13565990685219350708"
        },
        {
          "file": "apps/backend/project.json",
          "hash": "9233962208797548025"
        },
        {
          "file": "apps/backend/src/app/app.controller.spec.ts",
          "hash": "9499997688052526633",
          "deps": [
            "npm:@nestjs/testing"
          ]
        },
        {
          "file": "apps/backend/src/app/app.controller.ts",
          "hash": "9005150069945785676",
          "deps": [
            "npm:@nestjs/common"
          ]
        },
        {
          "file": "apps/backend/src/app/app.module.ts",
          "hash": "3163250445227373966",
          "deps": [
            "npm:@nestjs/common"
          ]
        },
        {
          "file": "apps/backend/src/app/app.service.spec.ts",
          "hash": "8587461140686713758",
          "deps": [
            "npm:@nestjs/testing"
          ]
        },
        {
          "file": "apps/backend/src/app/app.service.ts",
          "hash": "9967902337593410053",
          "deps": [
            "npm:@nestjs/common"
          ]
        },
        {
          "file": "apps/backend/src/assets/.gitkeep",
          "hash": "3244421341483603138"
        },
        {
          "file": "apps/backend/src/main.ts",
          "hash": "11205222914964382693",
          "deps": [
            "npm:@nestjs/common",
            "npm:@nestjs/core"
          ]
        },
        {
          "file": "apps/backend/tsconfig.app.json",
          "hash": "3171572500325445971"
        },
        {
          "file": "apps/backend/tsconfig.json",
          "hash": "3490524966360018312"
        },
        {
          "file": "apps/backend/tsconfig.spec.json",
          "hash": "11550347367511341917"
        },
        {
          "file": "apps/backend/webpack.config.js",
          "hash": "14532450057953654847",
          "deps": [
            "npm:@nx/webpack",
            "npm:path"
          ]
        }
      ],
      "frontend": [
        {
          "file": "apps/frontend/.eslintrc.json",
          "hash": "11012487992710232822"
        },
        {
          "file": "apps/frontend/index.html",
          "hash": "2323699249478598756"
        },
        {
          "file": "apps/frontend/postcss.config.js",
          "hash": "2759402739052110475",
          "deps": [
            "npm:path"
          ]
        },
        {
          "file": "apps/frontend/project.json",
          "hash": "1581687993160957088"
        },
        {
          "file": "apps/frontend/public/favicon.ico",
          "hash": "9303420814833116677"
        },
        {
          "file": "apps/frontend/src/app/app.spec.tsx",
          "hash": "18303175862115286083",
          "deps": [
            "npm:@testing-library/react"
          ]
        },
        {
          "file": "apps/frontend/src/app/app.tsx",
          "hash": "9598088391757195800"
        },
        {
          "file": "apps/frontend/src/app/nx-welcome.tsx",
          "hash": "729168762476089670"
        },
        {
          "file": "apps/frontend/src/assets/.gitkeep",
          "hash": "3244421341483603138"
        },
        {
          "file": "apps/frontend/src/main.tsx",
          "hash": "4731961929376199421",
          "deps": [
            "npm:react",
            "npm:react-dom"
          ]
        },
        {
          "file": "apps/frontend/src/styles.css",
          "hash": "9540575453073076294"
        },
        {
          "file": "apps/frontend/tailwind.config.js",
          "hash": "13090734457927965885",
          "deps": [
            "npm:@nx/react",
            "npm:path"
          ]
        },
        {
          "file": "apps/frontend/tsconfig.app.json",
          "hash": "7232119452847825095"
        },
        {
          "file": "apps/frontend/tsconfig.json",
          "hash": "11166545116916107487"
        },
        {
          "file": "apps/frontend/tsconfig.spec.json",
          "hash": "9472099605191632308"
        },
        {
          "file": "apps/frontend/vite.config.ts",
          "hash": "3786566035490919127",
          "deps": [
            "npm:vite",
            "npm:@vitejs/plugin-react",
            "npm:@nx/vite"
          ]
        }
      ],
      "website": [
        {
          "file": "apps/website/.eslintrc.json",
          "hash": "3060393911192195517"
        },
        {
          "file": "apps/website/index.d.ts",
          "hash": "5498222895072842432"
        },
        {
          "file": "apps/website/jest.config.ts",
          "hash": "8832065715910226160"
        },
        {
          "file": "apps/website/next-env.d.ts",
          "hash": "5909181270615354023"
        },
        {
          "file": "apps/website/next.config.js",
          "hash": "17252635002163063865",
          "deps": [
            "npm:@nx/next"
          ]
        },
        {
          "file": "apps/website/project.json",
          "hash": "11770910079608409306"
        },
        {
          "file": "apps/website/public/.gitkeep",
          "hash": "3244421341483603138"
        },
        {
          "file": "apps/website/public/favicon.ico",
          "hash": "9303420814833116677"
        },
        {
          "file": "apps/website/specs/index.spec.tsx",
          "hash": "1288872939091782814",
          "deps": [
            "npm:react",
            "npm:@testing-library/react"
          ]
        },
        {
          "file": "apps/website/src/app/api/hello/route.ts",
          "hash": "495073956729887886"
        },
        {
          "file": "apps/website/src/app/global.css",
          "hash": "2063387531564215811"
        },
        {
          "file": "apps/website/src/app/layout.tsx",
          "hash": "5031265179556016441"
        },
        {
          "file": "apps/website/src/app/page.module.scss",
          "hash": "4786619528779355986"
        },
        {
          "file": "apps/website/src/app/page.tsx",
          "hash": "17811775862216885156"
        },
        {
          "file": "apps/website/tsconfig.json",
          "hash": "2199354216269911900"
        },
        {
          "file": "apps/website/tsconfig.spec.json",
          "hash": "6922413205408300107"
        }
      ]
    },
    "nonProjectFiles": [
      {
        "file": ".editorconfig",
        "hash": "5443105041930014821"
      },
      {
        "file": ".eslintignore",
        "hash": "7663861978715868291"
      },
      {
        "file": ".eslintrc.json",
        "hash": "17866138117546000433"
      },
      {
        "file": ".gitignore",
        "hash": "3766888840636852595"
      },
      {
        "file": ".prettierignore",
        "hash": "6527998082399918071"
      },
      {
        "file": ".prettierrc",
        "hash": "16267754514737964994"
      },
      {
        "file": ".vscode/extensions.json",
        "hash": "4637156562308165301"
      },
      {
        "file": "README.md",
        "hash": "13336693898588166342"
      },
      {
        "file": "apps/.gitkeep",
        "hash": "3244421341483603138"
      },
      {
        "file": "jest.config.ts",
        "hash": "3494843969422251966"
      },
      {
        "file": "jest.preset.js",
        "hash": "9430166341120122740"
      },
      {
        "file": "nx.json",
        "hash": "14127461876299512271"
      },
      {
        "file": "package-lock.json",
        "hash": "5266199399350034940"
      },
      {
        "file": "package.json",
        "hash": "12013596163282066767"
      },
      {
        "file": "tools/tsconfig.tools.json",
        "hash": "16088922570277978783"
      },
      {
        "file": "tsconfig.base.json",
        "hash": "16936441711144470533"
      },
      {
        "file": "vitest.workspace.ts",
        "hash": "7870362608836821141"
      }
    ]
  }
}
